setsuperuser/__init__.py
setsuperuser/settings.py
setsuperuser/management/__init__.py
setsuperuser/management/commands/__init__.py
setsuperuser/management/commands/setsuperuser.py
setsuperuser-1.0.0.dist-info/DESCRIPTION.rst
setsuperuser-1.0.0.dist-info/METADATA
setsuperuser-1.0.0.dist-info/RECORD
setsuperuser-1.0.0.dist-info/WHEEL
setsuperuser-1.0.0.dist-info/metadata.json
setsuperuser-1.0.0.dist-info/top_level.txt
setsuperuser-1.0.0.dist-info/zip-safe
